{
  "checkpoint": {
    "name": "repl_start",
    "timestamp": "20260123_091939",
    "created_at": "2026-01-23T09:19:39-08:00"
  },
  "task": {
    "id": "US-011",
    "title": "Comment composer",
    "description": "As a user, I want to add comments so communication is tracked.",
    "status": "in_progress",
    "notes": "Starting REPL cycle"
  },
  "git": {
    "branch": "ralph/helpdesk-web-frontend",
    "commit": "991b7e0330f26b1474c6ca88f3145ecc78720e3b",
    "dirty_files": 4,
    "staged_files": [],
    "modified_files": [
      ".ralph/context.json",
      ".ralph/repl/US-011_state.json",
      "prd.json",
      "progress.txt"
    ]
  }
}
